fastapi_rowsecurity/__init__.py
fastapi_rowsecurity/create_policies.py
fastapi_rowsecurity/principals.py
fastapi_rowsecurity/register_rls.py
fastapi_rowsecurity/schemas.py
fastapi_rowsecurity-0.1b2.dist-info/LICENSE.txt
fastapi_rowsecurity-0.1b2.dist-info/METADATA
fastapi_rowsecurity-0.1b2.dist-info/WHEEL
fastapi_rowsecurity-0.1b2.dist-info/top_level.txt
fastapi_rowsecurity-0.1b2.dist-info/RECORD
