Metadata-Version: 2.1
Name: fastapi-rowsecurity
Version: 0.1b2
Summary: Row-Level Security (RLS) in SQLAlchemy.
Home-page: https://github.com/JWDobken/fastapi-rowsecurity
Author: jwdobken
Author-email: joost@dobken.nl
License: MIT
Project-URL: Documentation, https://github.com/JWDobken/fastapi-rowsecurity
Project-URL: Source, https://github.com/JWDobken/fastapi-rowsecurity
Platform: any
Classifier: Development Status :: 4 - Beta
Classifier: Programming Language :: Python
License-File: LICENSE.txt
Requires-Dist: pydantic >=2.5
Requires-Dist: sqlalchemy
Requires-Dist: importlib-metadata ; python_version < "3.8"
Provides-Extra: testing
Requires-Dist: setuptools ; extra == 'testing'
Requires-Dist: pytest ; extra == 'testing'
Requires-Dist: pytest-cov ; extra == 'testing'
Requires-Dist: pytest-asyncio ; extra == 'testing'
Requires-Dist: faker ; extra == 'testing'
Requires-Dist: asyncpg ; extra == 'testing'
Requires-Dist: greenlet ; extra == 'testing'
Requires-Dist: alembic ; extra == 'testing'
